odoo10_addon_sale_order_lot_mrp-10.0.1.0.0.99.dev8-py3.8-nspkg.pth
odoo/addons/sale_order_lot_mrp/README.rst
odoo/addons/sale_order_lot_mrp/__init__.py
odoo/addons/sale_order_lot_mrp/__manifest__.py
odoo/addons/sale_order_lot_mrp/i18n/ca.po
odoo/addons/sale_order_lot_mrp/i18n/de.po
odoo/addons/sale_order_lot_mrp/i18n/es.po
odoo/addons/sale_order_lot_mrp/i18n/es_ES.po
odoo/addons/sale_order_lot_mrp/i18n/es_MX.po
odoo/addons/sale_order_lot_mrp/i18n/fi.po
odoo/addons/sale_order_lot_mrp/i18n/fr.po
odoo/addons/sale_order_lot_mrp/i18n/gl.po
odoo/addons/sale_order_lot_mrp/i18n/hr.po
odoo/addons/sale_order_lot_mrp/i18n/it.po
odoo/addons/sale_order_lot_mrp/i18n/pt.po
odoo/addons/sale_order_lot_mrp/i18n/pt_BR.po
odoo/addons/sale_order_lot_mrp/i18n/pt_PT.po
odoo/addons/sale_order_lot_mrp/i18n/ro.po
odoo/addons/sale_order_lot_mrp/i18n/sale_order_lot_mrp.pot
odoo/addons/sale_order_lot_mrp/i18n/sl.po
odoo/addons/sale_order_lot_mrp/i18n/tr.po
odoo/addons/sale_order_lot_mrp/i18n/tr_TR.po
odoo/addons/sale_order_lot_mrp/i18n/vi_VN.po
odoo/addons/sale_order_lot_mrp/i18n/zh_CN.po
odoo/addons/sale_order_lot_mrp/models/__init__.py
odoo/addons/sale_order_lot_mrp/models/mrp.py
odoo/addons/sale_order_lot_mrp/models/procurement_order.py
odoo/addons/sale_order_lot_mrp/models/stock.py
odoo/addons/sale_order_lot_mrp/static/description/icon.png
odoo/addons/sale_order_lot_mrp/static/description/so_mrp_lot-1.png
odoo/addons/sale_order_lot_mrp/static/description/so_mrp_lot-2.png
odoo/addons/sale_order_lot_mrp/static/description/so_mrp_lot-3.png
odoo/addons/sale_order_lot_mrp/static/description/so_mrp_lot-4.png
odoo/addons/sale_order_lot_mrp/static/description/so_mrp_lot-5.png
odoo/addons/sale_order_lot_mrp/static/description/so_mrp_lot-6.png
odoo/addons/sale_order_lot_mrp/static/description/so_mrp_lot-7.png
odoo/addons/sale_order_lot_mrp/static/description/so_mrp_lot-8.png
odoo/addons/sale_order_lot_mrp/static/description/so_mrp_lot-9.png
odoo/addons/sale_order_lot_mrp/tests/__init__.py
odoo10_addon_sale_order_lot_mrp-10.0.1.0.0.99.dev8.dist-info/METADATA
odoo10_addon_sale_order_lot_mrp-10.0.1.0.0.99.dev8.dist-info/WHEEL
odoo10_addon_sale_order_lot_mrp-10.0.1.0.0.99.dev8.dist-info/namespace_packages.txt
odoo10_addon_sale_order_lot_mrp-10.0.1.0.0.99.dev8.dist-info/top_level.txt
odoo10_addon_sale_order_lot_mrp-10.0.1.0.0.99.dev8.dist-info/RECORD
